odoo8_addon_l10n_fr_tax_sale_ttc-8.0.0.1.0-py2.7-nspkg.pth
odoo8_addon_l10n_fr_tax_sale_ttc-8.0.0.1.0.dist-info/top_level.txt
odoo8_addon_l10n_fr_tax_sale_ttc-8.0.0.1.0.dist-info/WHEEL
odoo8_addon_l10n_fr_tax_sale_ttc-8.0.0.1.0.dist-info/RECORD
odoo8_addon_l10n_fr_tax_sale_ttc-8.0.0.1.0.dist-info/metadata.json
odoo8_addon_l10n_fr_tax_sale_ttc-8.0.0.1.0.dist-info/DESCRIPTION.rst
odoo8_addon_l10n_fr_tax_sale_ttc-8.0.0.1.0.dist-info/METADATA
odoo8_addon_l10n_fr_tax_sale_ttc-8.0.0.1.0.dist-info/namespace_packages.txt
odoo_addons/l10n_fr_tax_sale_ttc/__openerp__.py
odoo_addons/l10n_fr_tax_sale_ttc/__init__.py
odoo_addons/l10n_fr_tax_sale_ttc/README.rst
odoo_addons/l10n_fr_tax_sale_ttc/fr_tax.xml
